{
    "expt": {
        "exptname": "go_fish",
        "exptversion": 2,
        "sona_experiment_id": "1889",
        "sona_credit_token": "dc56fda841254cf7b818f6074c925e46"
    },
    "client": {
        "test": false,
        "sid": "user_1595889249516",
        "sona_survey_code": "31957"
    },
    "trials": {
        "is_test": false,
        "is_control": false,
        "expt_start_ts": 1595889249517,
        "instruction_data": {
            "instruction_start_ts": 1595889249517,
            "instruction_end_ts": 1595889272782
        },
        "trial_start_ts": 1595889272782,
        "trial_data": [
            {
                "trial_index": 1,
                "trial_n_start_ts": 1595889272990,
                "evidence_shape": {
                    "top_shape": "teardrop",
                    "top_color": "red",
                    "top_texture": true,
                    "bottom_shape": "triangle",
                    "bottom_color": "yellow",
                    "bottom_texture": false
                },
                "evidence_catches_fish": 1,
                "input_evidence_response": "bait\n",
                "evidence_resp_start_ts": 1595889279437,
                "evidence_resp_end_ts": 1595889292745,
                "prediction_start_ts": 1595889292746,
                "prediction_shape": {
                    "top_shape": "teardrop",
                    "top_color": "red",
                    "top_texture": true,
                    "bottom_shape": "diamond",
                    "bottom_color": "green",
                    "bottom_texture": false
                },
                "prediction_catches_fish": 1,
                "input_prediction_catches_fish": 1,
                "input_prediction_conf": 4,
                "prediction_end_ts": 1595889307479,
                "trial_n_end_ts": 1595889307479
            },
            {
                "trial_index": 2,
                "trial_n_start_ts": 1595889307479,
                "evidence_shape": {
                    "top_shape": "circle",
                    "top_color": "green",
                    "top_texture": false,
                    "bottom_shape": "teardrop",
                    "bottom_color": "blue",
                    "bottom_texture": false
                },
                "evidence_catches_fish": 0,
                "input_evidence_response": "didnt have right lure",
                "evidence_resp_start_ts": 1595889314095,
                "evidence_resp_end_ts": 1595889324772,
                "prediction_start_ts": 1595889324772,
                "prediction_shape": {
                    "top_shape": "circle",
                    "top_color": "green",
                    "top_texture": false,
                    "bottom_shape": "triangle",
                    "bottom_color": "red",
                    "bottom_texture": false
                },
                "prediction_catches_fish": 1,
                "input_prediction_catches_fish": 0,
                "input_prediction_conf": 4,
                "prediction_end_ts": 1595889334162,
                "trial_n_end_ts": 1595889334162
            },
            {
                "trial_index": 3,
                "trial_n_start_ts": 1595889334162,
                "evidence_shape": {
                    "top_shape": "diamond",
                    "top_color": "yellow",
                    "top_texture": false,
                    "bottom_shape": "circle",
                    "bottom_color": "green",
                    "bottom_texture": true
                },
                "evidence_catches_fish": 0,
                "input_evidence_response": "not the right lure",
                "evidence_resp_start_ts": 1595889337205,
                "evidence_resp_end_ts": 1595889345069,
                "prediction_start_ts": 1595889345070,
                "prediction_shape": {
                    "top_shape": "triangle",
                    "top_color": "yellow",
                    "top_texture": false,
                    "bottom_shape": "circle",
                    "bottom_color": "green",
                    "bottom_texture": true
                },
                "prediction_catches_fish": 0,
                "input_prediction_catches_fish": 0,
                "input_prediction_conf": 4,
                "prediction_end_ts": 1595889350873,
                "trial_n_end_ts": 1595889350873
            },
            {
                "trial_index": 4,
                "trial_n_start_ts": 1595889350874,
                "evidence_shape": {
                    "top_shape": "oval",
                    "top_color": "blue",
                    "top_texture": false,
                    "bottom_shape": "star",
                    "bottom_color": "yellow",
                    "bottom_texture": true
                },
                "evidence_catches_fish": 1,
                "input_evidence_response": "yellow end",
                "evidence_resp_start_ts": 1595889353745,
                "evidence_resp_end_ts": 1595889363321,
                "prediction_start_ts": 1595889363322,
                "prediction_shape": {
                    "top_shape": "oval",
                    "top_color": "blue",
                    "top_texture": false,
                    "bottom_shape": "teardrop",
                    "bottom_color": "red",
                    "bottom_texture": true
                },
                "prediction_catches_fish": 0,
                "input_prediction_catches_fish": 0,
                "input_prediction_conf": 4,
                "prediction_end_ts": 1595889369499,
                "trial_n_end_ts": 1595889369499
            },
            {
                "trial_index": 5,
                "trial_n_start_ts": 1595889369500,
                "evidence_shape": {
                    "top_shape": "circle",
                    "top_color": "red",
                    "top_texture": true,
                    "bottom_shape": "diamond",
                    "bottom_color": "green",
                    "bottom_texture": true
                },
                "evidence_catches_fish": 1,
                "input_evidence_response": "red lure",
                "evidence_resp_start_ts": 1595889373548,
                "evidence_resp_end_ts": 1595889380891,
                "prediction_start_ts": 1595889380891,
                "prediction_shape": {
                    "top_shape": "circle",
                    "top_color": "red",
                    "top_texture": true,
                    "bottom_shape": "teardrop",
                    "bottom_color": "blue",
                    "bottom_texture": false
                },
                "prediction_catches_fish": 0,
                "input_prediction_catches_fish": 1,
                "input_prediction_conf": 4,
                "prediction_end_ts": 1595889386183,
                "trial_n_end_ts": 1595889386183
            },
            {
                "trial_index": 6,
                "trial_n_start_ts": 1595889386184,
                "evidence_shape": {
                    "top_shape": "star",
                    "top_color": "blue",
                    "top_texture": false,
                    "bottom_shape": "circle",
                    "bottom_color": "red",
                    "bottom_texture": false
                },
                "evidence_catches_fish": 0,
                "input_evidence_response": "red end",
                "evidence_resp_start_ts": 1595889388981,
                "evidence_resp_end_ts": 1595889396075,
                "prediction_start_ts": 1595889396075,
                "prediction_shape": {
                    "top_shape": "star",
                    "top_color": "blue",
                    "top_texture": false,
                    "bottom_shape": "star",
                    "bottom_color": "yellow",
                    "bottom_texture": true
                },
                "prediction_catches_fish": 1,
                "input_prediction_catches_fish": 1,
                "input_prediction_conf": 4,
                "prediction_end_ts": 1595889403127,
                "trial_n_end_ts": 1595889403127
            },
            {
                "trial_index": 7,
                "trial_n_start_ts": 1595889403127,
                "evidence_shape": {
                    "top_shape": "diamond",
                    "top_color": "yellow",
                    "top_texture": true,
                    "bottom_shape": "diamond",
                    "bottom_color": "blue",
                    "bottom_texture": false
                },
                "evidence_catches_fish": 1,
                "input_evidence_response": "square lure",
                "evidence_resp_start_ts": 1595889406276,
                "evidence_resp_end_ts": 1595889431437,
                "prediction_start_ts": 1595889431437,
                "prediction_shape": {
                    "top_shape": "star",
                    "top_color": "green",
                    "top_texture": false,
                    "bottom_shape": "diamond",
                    "bottom_color": "blue",
                    "bottom_texture": false
                },
                "prediction_catches_fish": 1,
                "input_prediction_catches_fish": 0,
                "input_prediction_conf": 4,
                "prediction_end_ts": 1595889436211,
                "trial_n_end_ts": 1595889436211
            },
            {
                "trial_index": 8,
                "trial_n_start_ts": 1595889436211,
                "evidence_shape": {
                    "top_shape": "triangle",
                    "top_color": "green",
                    "top_texture": true,
                    "bottom_shape": "oval",
                    "bottom_color": "red",
                    "bottom_texture": true
                },
                "evidence_catches_fish": 0,
                "input_evidence_response": "only one circle on lure",
                "evidence_resp_start_ts": 1595889438447,
                "evidence_resp_end_ts": 1595889455256,
                "prediction_start_ts": 1595889455256,
                "prediction_shape": {
                    "top_shape": "diamond",
                    "top_color": "yellow",
                    "top_texture": false,
                    "bottom_shape": "oval",
                    "bottom_color": "red",
                    "bottom_texture": true
                },
                "prediction_catches_fish": 0,
                "input_prediction_catches_fish": 1,
                "input_prediction_conf": 4,
                "prediction_end_ts": 1595889461851,
                "trial_n_end_ts": 1595889461851
            }
        ],
        "trial_end_ts": 1595889461852,
        "evaluation_data": {
            "eval_ratings": [
                {
                    "eval_index": 1,
                    "eval_id": 1,
                    "eval_n_start_ts": 1595889461854,
                    "rule_text": "If a lure combination has a blue shape, it will catch fish.",
                    "category": "misc",
                    "evidence": 0.5,
                    "input_rule_rating": 61,
                    "eval_n_end_ts": 1595889466649
                },
                {
                    "eval_index": 2,
                    "eval_id": 5,
                    "eval_n_start_ts": 1595889466649,
                    "rule_text": "If a lure combination has a red shape on the bottom, it will catch fish.",
                    "category": "misc",
                    "evidence": 0.25,
                    "input_rule_rating": 57,
                    "eval_n_end_ts": 1595889470945
                },
                {
                    "eval_index": 3,
                    "eval_id": 7,
                    "eval_n_start_ts": 1595889470946,
                    "rule_text": "If a lure combination has a rounded top shape that resembles a fish's body, it will catch fish.",
                    "category": "abstract_shape",
                    "evidence": 0.75,
                    "input_rule_rating": 44,
                    "eval_n_end_ts": 1595889472423
                },
                {
                    "eval_index": 4,
                    "eval_id": 6,
                    "eval_n_start_ts": 1595889472423,
                    "rule_text": "If a lure combination has a purple dot on at least one of the lures, it will catch fish.",
                    "category": "misc",
                    "evidence": 0.75,
                    "input_rule_rating": 61,
                    "eval_n_end_ts": 1595889473898
                },
                {
                    "eval_index": 5,
                    "eval_id": 3,
                    "eval_n_start_ts": 1595889473899,
                    "rule_text": "If a lure combination has a top lure with bright colors that are more visible under water (red or yellow), it will catch fish.",
                    "category": "abstract_color",
                    "evidence": 0.75,
                    "input_rule_rating": 69,
                    "eval_n_end_ts": 1595889477327
                },
                {
                    "eval_index": 6,
                    "eval_id": 8,
                    "eval_n_start_ts": 1595889477328,
                    "rule_text": "There is no pattern to which lure combinations catch fish: the results are random, but there are approximately equal numbers that catch fish and don\u2019t.",
                    "category": "rand",
                    "evidence": 0,
                    "input_rule_rating": 60,
                    "eval_n_end_ts": 1595889479688
                },
                {
                    "eval_index": 7,
                    "eval_id": 2,
                    "eval_n_start_ts": 1595889479689,
                    "rule_text": "If a lure combination has a yellow shape or a diamond on the bottom, it will catch fish.",
                    "category": "distractor",
                    "evidence": 1,
                    "input_rule_rating": 51,
                    "eval_n_end_ts": 1595889481947
                },
                {
                    "eval_index": 8,
                    "eval_id": 4,
                    "eval_n_start_ts": 1595889481947,
                    "rule_text": "If a lure combination has a pointy shape on the bottom, it will catch fish.",
                    "category": "target",
                    "evidence": 1,
                    "input_rule_rating": 51,
                    "eval_n_end_ts": 1595889484155
                }
            ],
            "evaluation_start_ts": 1595889461854,
            "evaluation_end_ts": 1595889484155
        },
        "memory_data": {
            "memory_responses": [
                {
                    "memory_shape": {
                        "top_shape": "teardrop",
                        "top_color": "yellow",
                        "top_texture": false,
                        "bottom_shape": "diamond",
                        "bottom_color": "green",
                        "bottom_texture": false
                    },
                    "memory_shape_in_expt": 0,
                    "memory_shape_catches_fish": 1,
                    "input_shape_in_expt": 0
                },
                {
                    "memory_shape": {
                        "top_shape": "triangle",
                        "top_color": "yellow",
                        "top_texture": false,
                        "bottom_shape": "circle",
                        "bottom_color": "green",
                        "bottom_texture": true
                    },
                    "memory_shape_in_expt": 1,
                    "memory_shape_catches_fish": 0,
                    "input_shape_in_expt": 1
                },
                {
                    "memory_shape": {
                        "top_shape": "oval",
                        "top_color": "green",
                        "top_texture": false,
                        "bottom_shape": "diamond",
                        "bottom_color": "red",
                        "bottom_texture": true
                    },
                    "memory_shape_in_expt": 0,
                    "memory_shape_catches_fish": 1,
                    "input_shape_in_expt": 1
                },
                {
                    "memory_shape": {
                        "top_shape": "teardrop",
                        "top_color": "red",
                        "top_texture": true,
                        "bottom_shape": "triangle",
                        "bottom_color": "yellow",
                        "bottom_texture": false
                    },
                    "memory_shape_in_expt": 1,
                    "memory_shape_catches_fish": 1,
                    "input_shape_in_expt": 1
                },
                {
                    "memory_shape": {
                        "top_shape": "diamond",
                        "top_color": "blue",
                        "top_texture": false,
                        "bottom_shape": "circle",
                        "bottom_color": "blue",
                        "bottom_texture": false
                    },
                    "memory_shape_in_expt": 0,
                    "memory_shape_catches_fish": 0,
                    "input_shape_in_expt": 0
                },
                {
                    "memory_shape": {
                        "top_shape": "star",
                        "top_color": "blue",
                        "top_texture": false,
                        "bottom_shape": "circle",
                        "bottom_color": "red",
                        "bottom_texture": false
                    },
                    "memory_shape_in_expt": 1,
                    "memory_shape_catches_fish": 0,
                    "input_shape_in_expt": 0
                },
                {
                    "memory_shape": {
                        "top_shape": "circle",
                        "top_color": "yellow",
                        "top_texture": false,
                        "bottom_shape": "oval",
                        "bottom_color": "yellow",
                        "bottom_texture": false
                    },
                    "memory_shape_in_expt": 0,
                    "memory_shape_catches_fish": 0,
                    "input_shape_in_expt": 0
                },
                {
                    "memory_shape": {
                        "top_shape": "star",
                        "top_color": "blue",
                        "top_texture": false,
                        "bottom_shape": "star",
                        "bottom_color": "yellow",
                        "bottom_texture": true
                    },
                    "memory_shape_in_expt": 1,
                    "memory_shape_catches_fish": 1,
                    "input_shape_in_expt": 1
                }
            ],
            "memory_start_ts": 1595889484156,
            "memory_end_ts": 1595889498080
        },
        "expt_end_ts": 1595889498081
    }
}